Metadata-Version: 2.4
Name: getstream-plugins-deepgram
Version: 0.1.1
Summary: Deepgram plugin for GetStream
License-Expression: MIT
Requires-Python: >=3.10
Requires-Dist: deepgram-sdk>=4.5.0
Requires-Dist: getstream-plugins-common>=0.1.1
Requires-Dist: getstream[webrtc]>=2.3.0a4
Requires-Dist: numpy<2.3,>=2.2.6
